yt_channel_downloader/__init__.py
yt_channel_downloader/__main__.py
yt_channel_downloader/icon.png
yt_channel_downloader/assets/__init__.py
yt_channel_downloader/assets/icon.png
yt_channel_downloader/assets/resources.qrc
yt_channel_downloader/assets/resources_rc.py
yt_channel_downloader/assets/youtube-icon.png
yt_channel_downloader/assets/__pycache__/__init__.cpython-310.pyc
yt_channel_downloader/assets/__pycache__/resources_rc.cpython-310.pyc
yt_channel_downloader/assets/icons/icon.ico
yt_channel_downloader/assets/icons/icon.png
yt_channel_downloader/classes/YTChannel.py
yt_channel_downloader/classes/__init__.py
yt_channel_downloader/classes/auto_update_worker.py
yt_channel_downloader/classes/browser_config.py
yt_channel_downloader/classes/checkbox_delegate.py
yt_channel_downloader/classes/custom_dialog.py
yt_channel_downloader/classes/download_thread.py
yt_channel_downloader/classes/enums.py
yt_channel_downloader/classes/fetch_progress_dialog.py
yt_channel_downloader/classes/ffmpeg_checker.py
yt_channel_downloader/classes/get_list_thread.py
yt_channel_downloader/classes/js_warning_tracker.py
yt_channel_downloader/classes/logger.py
yt_channel_downloader/classes/login_prompt_dialog.py
yt_channel_downloader/classes/mainwindow.py
yt_channel_downloader/classes/node_runtime_notifier.py
yt_channel_downloader/classes/progress_bar_delegate.py
yt_channel_downloader/classes/quiet_ydl_logger.py
yt_channel_downloader/classes/release_info.py
yt_channel_downloader/classes/runtime_info.py
yt_channel_downloader/classes/runtime_mode.py
yt_channel_downloader/classes/selection_size_worker.py
yt_channel_downloader/classes/settings.py
yt_channel_downloader/classes/settings_manager.py
yt_channel_downloader/classes/support_prompt.py
yt_channel_downloader/classes/thumbnail_loader.py
yt_channel_downloader/classes/update_context.py
yt_channel_downloader/classes/update_fetch_error.py
yt_channel_downloader/classes/update_result.py
yt_channel_downloader/classes/update_status.py
yt_channel_downloader-0.8.6.dist-info/licenses/LICENSE
yt_channel_downloader-0.8.6.dist-info/METADATA
yt_channel_downloader-0.8.6.dist-info/WHEEL
yt_channel_downloader-0.8.6.dist-info/entry_points.txt
yt_channel_downloader-0.8.6.dist-info/top_level.txt
yt_channel_downloader-0.8.6.dist-info/RECORD
