Metadata-Version: 2.4
Name: yt-channel-downloader
Version: 0.8.6
Summary: Desktop app for downloading entire YouTube channels or playlists via yt-dlp.
Author-email: hyperfield <info@quicknode.net>
License: MIT License
Project-URL: Homepage, https://github.com/hyperfield/yt-channel-downloader
Project-URL: Source, https://github.com/hyperfield/yt-channel-downloader
Project-URL: Issues, https://github.com/hyperfield/yt-channel-downloader/issues
Keywords: youtube,yt-dlp,downloader,video,gui,PyQt6
Classifier: Development Status :: 4 - Beta
Classifier: Intended Audience :: End Users/Desktop
Classifier: License :: OSI Approved :: MIT License
Classifier: Programming Language :: Python
Classifier: Programming Language :: Python :: 3
Classifier: Programming Language :: Python :: 3.9
Classifier: Programming Language :: Python :: 3.10
Classifier: Programming Language :: Python :: 3.11
Classifier: Programming Language :: Python :: 3.12
Classifier: Programming Language :: Python :: 3.13
Classifier: Operating System :: OS Independent
Classifier: Topic :: Multimedia :: Video
Classifier: Environment :: X11 Applications :: Qt
Requires-Python: >=3.9
License-File: LICENSE
Requires-Dist: appdirs>=1.4.4
Requires-Dist: requests>=2.31
Requires-Dist: yt-dlp>=2025.11.12
Requires-Dist: PyQt6>=6.6.0
Provides-Extra: test
Requires-Dist: pytest>=7.4; extra == "test"
Dynamic: license-file
